jupyter_floating_chat/__init__.py
jupyter_floating_chat/_version.py
jupyter_floating_chat-0.1.1.data/data/share/jupyter/labextensions/jupyter-floating-chat/package.json
jupyter_floating_chat-0.1.1.data/data/share/jupyter/labextensions/jupyter-floating-chat/schemas/jupyter-floating-chat/package.json.orig
jupyter_floating_chat-0.1.1.data/data/share/jupyter/labextensions/jupyter-floating-chat/schemas/jupyter-floating-chat/plugin.json
jupyter_floating_chat-0.1.1.data/data/share/jupyter/labextensions/jupyter-floating-chat/static/195.2fedd7342d4310189268.js
jupyter_floating_chat-0.1.1.data/data/share/jupyter/labextensions/jupyter-floating-chat/static/483.7d62c3e9dc03e6c42cd7.js
jupyter_floating_chat-0.1.1.data/data/share/jupyter/labextensions/jupyter-floating-chat/static/483.7d62c3e9dc03e6c42cd7.js.LICENSE.txt
jupyter_floating_chat-0.1.1.data/data/share/jupyter/labextensions/jupyter-floating-chat/static/728.53d5712ffbc53338f2b6.js
jupyter_floating_chat-0.1.1.data/data/share/jupyter/labextensions/jupyter-floating-chat/static/remoteEntry.136b24a482587f86825a.js
jupyter_floating_chat-0.1.1.data/data/share/jupyter/labextensions/jupyter-floating-chat/static/style.js
jupyter_floating_chat-0.1.1.data/data/share/jupyter/labextensions/jupyter-floating-chat/static/third-party-licenses.json
jupyter_floating_chat-0.1.1.data/data/share/jupyter/labextensions/jupyter-floating-chat/install.json
jupyter_floating_chat-0.1.1.dist-info/METADATA
jupyter_floating_chat-0.1.1.dist-info/WHEEL
jupyter_floating_chat-0.1.1.dist-info/licenses/LICENSE
jupyter_floating_chat-0.1.1.dist-info/RECORD
