Metadata-Version: 2.4
Name: jupyter_floating_chat
Version: 0.1.1
Summary: A JupyterLab extension to add a floating chat.
Project-URL: Homepage, https://github.com/jupyter-ai-contrib/jupyter-floating-chat
Project-URL: Bug Tracker, https://github.com/jupyter-ai-contrib/jupyter-floating-chat/issues
Project-URL: Repository, https://github.com/jupyter-ai-contrib/jupyter-floating-chat.git
Author-email: Project Jupyter <jupyter@googlegroups.com>
License: BSD 3-Clause License
License-File: LICENSE
Keywords: jupyter,jupyterlab,jupyterlab-extension
Classifier: Framework :: Jupyter
Classifier: Framework :: Jupyter :: JupyterLab
Classifier: Framework :: Jupyter :: JupyterLab :: 4
Classifier: Framework :: Jupyter :: JupyterLab :: Extensions
Classifier: Framework :: Jupyter :: JupyterLab :: Extensions :: Prebuilt
Classifier: License :: OSI Approved :: BSD License
Classifier: Programming Language :: Python
Classifier: Programming Language :: Python :: 3
Classifier: Programming Language :: Python :: 3.9
Classifier: Programming Language :: Python :: 3.10
Classifier: Programming Language :: Python :: 3.11
Classifier: Programming Language :: Python :: 3.12
Classifier: Programming Language :: Python :: 3.13
Requires-Python: >=3.9
